Metadata-Version: 2.1
Name: Shpresa
Version: 1.0.2
Summary: Python Distribution Utilities
Home-page: https://www.python.org/sigs/distutils-sig/
Author: SHPRESA TUP
Author-email: SHPRESA@python.net
License: UNKNOWN
Platform: UNKNOWN
